sqlxray/__init__.py
sqlxray/sqlxray.py
sqlxray-0.1.1.dist-info/WHEEL
sqlxray-0.1.1.dist-info/METADATA
sqlxray-0.1.1.dist-info/RECORD
