Metadata-Version: 2.1
Name: sqlxray
Version: 0.1.1
Summary: 
Author: Khalid
Author-email: khalidck@gmail.com
Requires-Python: >=3.7,<4.0
Classifier: Programming Language :: Python :: 3
Classifier: Programming Language :: Python :: 3.7
Classifier: Programming Language :: Python :: 3.8
Requires-Dist: sqlparse (>=0.3.0,<0.4.0)
